Cargo.lock
Cargo.toml
LICENSE
MANIFEST.in
README.md
cargo_popat.ps1
gcc_popat.ps1
javac_popat.ps1
js.bat
node_popat.ps1
popat_integration.ps1
py.bat
pyproject.toml
python_popat.ps1
rustc_popat.ps1
setup.py
cli/Cargo.toml
cli/src/daemon.rs
cli/src/display.rs
cli/src/hooks.rs
cli/src/interceptor.rs
cli/src/main.rs
core/Cargo.toml
core/src/config.rs
core/src/error_parser.rs
core/src/error_parser_tests.rs
core/src/humor_engine.rs
core/src/humor_engine_tests.rs
core/src/learning.rs
core/src/learning_tests.rs
core/src/lib.rs
popat.egg-info/PKG-INFO
popat.egg-info/SOURCES.txt
popat.egg-info/dependency_links.txt
popat.egg-info/entry_points.txt
popat.egg-info/not-zip-safe
popat.egg-info/requires.txt
popat.egg-info/top_level.txt
popat_python/__init__.py
popat_python/cli.py
popat_python/popat.exe
popat_python/__pycache__/__init__.cpython-313.pyc
popat_python/__pycache__/cli.cpython-313.pyc