Metadata-Version: 2.2
Name: popat
Version: 0.1.3
Summary: Intelligent Terminal Error Helper - Advanced error detection and analysis for developers
Home-page: https://github.com/An1rud/popat
Author: Anirudh Sajith
Author-email: Popat Team <anirudhsajith03@gmail.com>
License: MIT
Project-URL: Homepage, https://github.com/An1rud/popat
Project-URL: Repository, https://github.com/An1rud/popat
Project-URL: Documentation, https://github.com/An1rud/popat#readme
Project-URL: Bug Reports, https://github.com/An1rud/popat/issues
Project-URL: Source Code, https://github.com/An1rud/popat
Project-URL: Download, https://pypi.org/project/popat/
Keywords: error,debugging,humor,terminal,ai,assistant
Classifier: Development Status :: 4 - Beta
Classifier: Intended Audience :: Developers
Classifier: Topic :: Software Development :: Debuggers
Classifier: Topic :: System :: Shells
Classifier: License :: OSI Approved :: MIT License
Classifier: Programming Language :: Python :: 3
Classifier: Programming Language :: Python :: 3.7
Classifier: Programming Language :: Python :: 3.8
Classifier: Programming Language :: Python :: 3.9
Classifier: Programming Language :: Python :: 3.10
Classifier: Programming Language :: Python :: 3.11
Classifier: Programming Language :: Rust
Classifier: Operating System :: OS Independent
Requires-Python: >=3.7
License-File: LICENSE
Requires-Dist: click>=8.0.0
Requires-Dist: colorama>=0.4.4
Requires-Dist: psutil>=5.8.0
Provides-Extra: dev
Requires-Dist: pytest>=6.0; extra == "dev"
Requires-Dist: black>=21.0; extra == "dev"
Requires-Dist: flake8>=3.9; extra == "dev"
Requires-Dist: mypy>=0.910; extra == "dev"
Dynamic: author
Dynamic: home-page
Dynamic: requires-python
